odoo8_addon_event_registration_partner_unique-8.0.1.0.0.99.dev3-py2.7-nspkg.pth
odoo8_addon_event_registration_partner_unique-8.0.1.0.0.99.dev3.dist-info/METADATA
odoo8_addon_event_registration_partner_unique-8.0.1.0.0.99.dev3.dist-info/RECORD
odoo8_addon_event_registration_partner_unique-8.0.1.0.0.99.dev3.dist-info/WHEEL
odoo8_addon_event_registration_partner_unique-8.0.1.0.0.99.dev3.dist-info/namespace_packages.txt
odoo8_addon_event_registration_partner_unique-8.0.1.0.0.99.dev3.dist-info/top_level.txt
odoo_addons/event_registration_partner_unique/README.rst
odoo_addons/event_registration_partner_unique/__init__.py
odoo_addons/event_registration_partner_unique/__openerp__.py
odoo_addons/event_registration_partner_unique/exceptions.py
odoo_addons/event_registration_partner_unique/i18n/es.po
odoo_addons/event_registration_partner_unique/models/__init__.py
odoo_addons/event_registration_partner_unique/models/event.py
odoo_addons/event_registration_partner_unique/static/description/icon.png
odoo_addons/event_registration_partner_unique/tests/__init__.py
odoo_addons/event_registration_partner_unique/tests/test_event.py
odoo_addons/event_registration_partner_unique/views/event_event_view.xml
